{
	"name": "df_DimCustomer",
	"properties": {
		"type": "MappingDataFlow",
		"typeProperties": {
			"sources": [
				{
					"dataset": {
						"referenceName": "appdb_dimcustomer",
						"type": "DatasetReference"
					},
					"name": "CustomerDim"
				}
			],
			"sinks": [
				{
					"dataset": {
						"referenceName": "DimCustomer_Table",
						"type": "DatasetReference"
					},
					"name": "DimCustomer"
				}
			],
			"transformations": [
				{
					"name": "filter1"
				}
			],
			"scriptLines": [
				"source(output(",
				"          CustomerId as integer,",
				"          CompanyName as string,",
				"          SalesPerson as string",
				"     ),",
				"     allowSchemaDrift: true,",
				"     validateSchema: false,",
				"     isolationLevel: 'READ_UNCOMMITTED',",
				"     format: 'table') ~> CustomerDim",
				"CustomerDim filter(CustomerId!=507) ~> filter1",
				"filter1 sink(allowSchemaDrift: true,",
				"     validateSchema: false,",
				"     input(",
				"          CustomerID as integer,",
				"          CompanyName as string,",
				"          SalesPerson as string",
				"     ),",
				"     deletable:false,",
				"     insertable:true,",
				"     updateable:false,",
				"     upsertable:false,",
				"     format: 'table',",
				"     staged: true,",
				"     allowCopyCommand: true,",
				"     skipDuplicateMapInputs: true,",
				"     skipDuplicateMapOutputs: true,",
				"     errorHandlingOption: 'stopOnFirstError',",
				"     mapColumn(",
				"          CustomerID = CustomerId,",
				"          CompanyName,",
				"          SalesPerson",
				"     )) ~> DimCustomer"
			]
		}
	}
}